Workbook

Sheet Dashboard
A1: DONECRM - DASHBOARD
A2: Mis à jour le: | B2: =TODAY()
A5: INDICATEURS CLÉS
A6: MRR (Monthly) | B6: ARR (Yearly) | C6: CA Total | D6: Marge
A7: =Clients!$K$2 | B7: =Clients!$L$2 | C7: =Clients!$H$2 | D7: =Clients!$H$2-Finances!$D$2
A9: Nbr Clients | B9: Nbr Prospects | C9: Nbr Leads
A10: =COUNTIF(Clients!E:E,"Client") | B10: =COUNTIF(Clients!E:E,"Prospect") | C10: =COUNTIF(Clients!E:E,"Lead")

Sheet Clients
A1: ID | B1: Nom | C1: Site | D1: Secteur | E1: Statut | F1: Source | G1: Contacté | H1: Montant Vente | I1: Abonnement | J1: Coût Replit | K1: MRR Total | L1: ARR Total | M1: Notes
A2: TOTAUX | H2: =SUM(H3:H1000) | I2: =SUM(I3:I1000) | J2: =SUM(J3:J1000) | K2: =I2 | L2: =K2*12
A3: =ROW()-2 | B3: Viveur | C3: https://viveur-liege.replit.app/ | D3: Horeca | E3: Lead | F3: Out | G3: Oui | H3: 0 | I3: 0 | J3: 15.681034 | K3: =I3 | L3: =K3*12
A4: =ROW()-2 | B4: DSV frites et burgers | C4: https://dsvburgers.be/ | D4: Horeca | E4: Client | F4: Out | G4: Oui | H4: 410.7438 | I4: 0 | J4: 120.68966 | K4: =I4 | L4: =K4*12
A5: =ROW()-2 | B5: Kuore | C5: https://kuore.replit.app/ | D5: Horeca | E5: Client | F5: Out | G5: Oui | H5: 245.45455 | I5: 16.446281 | J5: 2.362069 | K5: =I5 | L5: =K5*12
A6: =ROW()-2 | B6: Konno | C6: https://konno-liege.replit.app/ | D6: Horeca | E6: Lead | F6: Out | G6: Oui | H6: 0 | I6: 0 | J6: 2.5689655 | K6: =I6 | L6: =K6*12
A7: =ROW()-2 | B7: Laurelies,nails | C7: https://laureliesnails.replit.app/ | D7: Onglerie | E7: Lead | F7: Out | G7: Oui | H7: 0 | I7: 0 | J7: 0.40517241 | K7: =I7 | L7: =K7*12
A8: =ROW()-2 | B8: Ideal Fitness | C8: https://idealfitness.be | D8: Fitness | E8: Client | F8: Out | G8: Oui | H8: 245.45455 | I8: 0 | J8: 14.801724 | K8: =I8 | L8: =K8*12
A9: =ROW()-2 | B9: MaxMecaCars | C9: https://maxmecacars.replit.app/ | D9: Carrosserie | E9: Prospect | F9: Out | G9: Oui | H9: 0 | I9: 0 | J9: 2.8189655 | K9: =I9 | L9: =K9*12
A10: =ROW()-2 | B10: Moment | C10: https://moment-liege.replit.app/ | D10: Horeca | E10: Lead | F10: Out | G10: Oui | H10: 0 | I10: 0 | J10: 19.741379 | K10: =I10 | L10: =K10*12
A11: =ROW()-2 | B11: Mabelita Pizza | C11: https://mabelita-pizza.be/ | D11: Horeca | E11: Client | F11: Out | G11: Oui | H11: 245.45455 | I11: 16.446281 | J11: 12.353448 | K11: =I11 | L11: =K11*12
A12: =ROW()-2 | B12: Flak | C12: https://flak.madebydone.be/ | D12: Horeca | E12: Lead | F12: Out | G12: Oui | H12: 0 | I12: 0 | J12: 20.965517 | K12: =I12 | L12: =K12*12
A13: =ROW()-2 | B13: Danieli | C13: https://restaurantdanieli.be | D13: Horeca | E13: Client | F13: Out | G13: Oui | H13: 245.45455 | I13: 16.446281 | J13: 4.5172414 | K13: =I13 | L13: =K13*12
A14: =ROW()-2 | B14: Jéroboam | C14: https://jeroboam.madebydone.be | D14: Horeca | E14: Lead | F14: Out | G14: Oui | H14: 0 | I14: 0 | J14: 1 | K14: =I14 | L14: =K14*12
... A16: =ROW()-2 | B16: Aste | C16: https://aste-esthetique.be/ | D16: Esthétique | E16: Lead | F16: Out | G16: Non | H16: 0 | I16: 24.793388 | J16: 0 | K16: =I16 | L16: =K16*12

Sheet Pipeline
B1: LEADS | E1: PROSPECTS | H1: CLIENTS | K1: CHURNED
B2: =COUNTIF(Clients!E:E,"LEAD") | E2: =COUNTIF(Clients!E:E,"PROSPECT") | H2: =COUNTIF(Clients!E:E,"CLIENT") | K2: =COUNTIF(Clients!E:E,"CHURNE")

Sheet Finances
A1: SUIVI FINANCIER
D2: =B11
A3: COÛTS FIXES
A4: Meta Ads | B4: 100 | C4: €/mois
A5: Done (salaires) | B5: =(97.27/1.16)+6.99 | C5: €/mois
A7: COÛTS VARIABLES
A8: Total Replit | B8: =Clients!$J$2 | C8: €/mois
A9: Total Domaines | B9: 0 | C9: €/an
A11: TOTAL COÛTS | B11: =B4+B5+B8
A13: REVENUS
A14: Ventes Totales | B14: =Clients!$H$2
A15: MRR Total | B15: =Clients!$K$2
A16: ARR Total | B16: =Clients!$L$2
A18: MARGE | B18: =B14-B11

Sheet Import Original
A1: Données originales importées depuis Gestion_V1.xlsx
A2: Cette feuille contient les données brutes importées
